{
  "marcador": "2 : 0",
  "estadio": "BC Place Vancouver",
  "home": {
    "equipo": "Australia",
    "jugadores": [
      {
        "id": 481083,
        "nombre": "Mohamed Touré",
        "dorsal": 9,
        "x": 68.0,
        "y": 36.9,
        "toques": 24
      },
      {
        "id": 344380,
        "nombre": "Harry Souttar",
        "dorsal": 19,
        "x": 26.4,
        "y": 40.6,
        "toques": 52
      },
      {
        "id": 442302,
        "nombre": "Connor Metcalfe",
        "dorsal": 8,
        "x": 51.6,
        "y": 26.1,
        "toques": 48
      },
      {
        "id": 323097,
        "nombre": "Aiden O'Neill",
        "dorsal": 13,
        "x": 47.6,
        "y": 51.4,
        "toques": 51
      },
      {
        "id": 445546,
        "nombre": "Jacob Italiano",
        "dorsal": 4,
        "x": 39.8,
        "y": 17.4,
        "toques": 47
      },
      {
        "id": 447486,
        "nombre": "Alessandro Circati",
        "dorsal": 3,
        "x": 38.6,
        "y": 24.5,
        "toques": 60
      },
      {
        "id": 570078,
        "nombre": "Paul Okon-Engstler",
        "dorsal": 24,
        "x": 39.0,
        "y": 60.0,
        "toques": 66
      },
      {
        "id": 477369,
        "nombre": "Nestory Irankunda",
        "dorsal": 17,
        "x": 58.1,
        "y": 62.8,
        "toques": 23
      },
      {
        "id": 599694,
        "nombre": "Patrick Beach",
        "dorsal": 18,
        "x": 6.0,
        "y": 49.4,
        "toques": 64
      },
      {
        "id": 231118,
        "nombre": "Cameron Burgess",
        "dorsal": 21,
        "x": 22.2,
        "y": 71.3,
        "toques": 55
      },
      {
        "id": 476544,
        "nombre": "Jordan Bos",
        "dorsal": 5,
        "x": 44.8,
        "y": 81.3,
        "toques": 45
      }
    ],
    "pases": [
      {
        "de": 344380,
        "a": 481083,
        "veces": 1
      },
      {
        "de": 323097,
        "a": 442302,
        "veces": 4
      },
      {
        "de": 447486,
        "a": 570078,
        "veces": 6
      },
      {
        "de": 445546,
        "a": 447486,
        "veces": 10
      },
      {
        "de": 570078,
        "a": 599694,
        "veces": 2
      },
      {
        "de": 442302,
        "a": 599694,
        "veces": 2
      },
      {
        "de": 344380,
        "a": 599694,
        "veces": 4
      },
      {
        "de": 476544,
        "a": 599694,
        "veces": 3
      },
      {
        "de": 231118,
        "a": 476544,
        "veces": 13
      },
      {
        "de": 231118,
        "a": 344380,
        "veces": 13
      },
      {
        "de": 344380,
        "a": 447486,
        "veces": 7
      },
      {
        "de": 476544,
        "a": 570078,
        "veces": 14
      },
      {
        "de": 231118,
        "a": 599694,
        "veces": 13
      },
      {
        "de": 231118,
        "a": 477369,
        "veces": 1
      },
      {
        "de": 476544,
        "a": 477369,
        "veces": 4
      },
      {
        "de": 442302,
        "a": 445546,
        "veces": 5
      },
      {
        "de": 323097,
        "a": 445546,
        "veces": 4
      },
      {
        "de": 323097,
        "a": 570078,
        "veces": 11
      },
      {
        "de": 445546,
        "a": 476544,
        "veces": 2
      },
      {
        "de": 323097,
        "a": 476544,
        "veces": 9
      },
      {
        "de": 445546,
        "a": 570078,
        "veces": 2
      },
      {
        "de": 231118,
        "a": 570078,
        "veces": 14
      },
      {
        "de": 231118,
        "a": 442302,
        "veces": 1
      },
      {
        "de": 442302,
        "a": 476544,
        "veces": 3
      },
      {
        "de": 231118,
        "a": 447486,
        "veces": 6
      },
      {
        "de": 231118,
        "a": 323097,
        "veces": 9
      },
      {
        "de": 447486,
        "a": 599694,
        "veces": 5
      },
      {
        "de": 447486,
        "a": 481083,
        "veces": 1
      },
      {
        "de": 442302,
        "a": 447486,
        "veces": 5
      },
      {
        "de": 323097,
        "a": 481083,
        "veces": 1
      },
      {
        "de": 442302,
        "a": 481083,
        "veces": 1
      },
      {
        "de": 344380,
        "a": 442302,
        "veces": 1
      },
      {
        "de": 477369,
        "a": 570078,
        "veces": 5
      },
      {
        "de": 445546,
        "a": 481083,
        "veces": 2
      },
      {
        "de": 344380,
        "a": 445546,
        "veces": 3
      },
      {
        "de": 442302,
        "a": 477369,
        "veces": 1
      },
      {
        "de": 445546,
        "a": 599694,
        "veces": 1
      },
      {
        "de": 323097,
        "a": 447486,
        "veces": 4
      },
      {
        "de": 476544,
        "a": 481083,
        "veces": 1
      },
      {
        "de": 323097,
        "a": 344380,
        "veces": 5
      },
      {
        "de": 231118,
        "a": 481083,
        "veces": 1
      },
      {
        "de": 477369,
        "a": 481083,
        "veces": 1
      },
      {
        "de": 323097,
        "a": 477369,
        "veces": 2
      },
      {
        "de": 442302,
        "a": 570078,
        "veces": 1
      },
      {
        "de": 344380,
        "a": 570078,
        "veces": 1
      },
      {
        "de": 447486,
        "a": 476544,
        "veces": 1
      },
      {
        "de": 481083,
        "a": 570078,
        "veces": 1
      }
    ],
    "estadisticas": {
      "tiros": 9,
      "tiros_al_arco": 5,
      "pases_totales": 305,
      "precision_pases": 72.5,
      "posesion": 37.2,
      "goles": [
        {
          "minuto": 26,
          "jugador": "Nestory Irankunda"
        },
        {
          "minuto": 74,
          "jugador": "Connor Metcalfe"
        }
      ]
    },
    "tiros": [
      {
        "minuto": 16,
        "jugador": "Alessandro Circati",
        "resultado": "MissedShots",
        "x": 94.3,
        "y": 55.8,
        "arco_y": 65.2,
        "arco_z": 52.8
      },
      {
        "minuto": 26,
        "jugador": "Nestory Irankunda",
        "resultado": "Goal",
        "x": 87.0,
        "y": 56.4,
        "arco_y": 53.4,
        "arco_z": 1.9
      },
      {
        "minuto": 38,
        "jugador": "Jordan Bos",
        "resultado": "MissedShots",
        "x": 74.9,
        "y": 53.8,
        "arco_y": 57.1,
        "arco_z": 79.2
      },
      {
        "minuto": 44,
        "jugador": "Nestory Irankunda",
        "resultado": "SavedShot",
        "x": 83.7,
        "y": 56.2,
        "arco_y": 50.9,
        "arco_z": 6.3
      },
      {
        "minuto": 47,
        "jugador": "Jordan Bos",
        "resultado": "SavedShot",
        "x": 88.5,
        "y": 67.1,
        "arco_y": 48.2,
        "arco_z": 18.1
      },
      {
        "minuto": 48,
        "jugador": "Jacob Italiano",
        "resultado": "MissedShots",
        "x": 77.7,
        "y": 64.6,
        "arco_y": 35.0,
        "arco_z": 94.4
      },
      {
        "minuto": 53,
        "jugador": "Harry Souttar",
        "resultado": "SavedShot",
        "x": 89.8,
        "y": 41.2,
        "arco_y": 51.3,
        "arco_z": 15.2
      },
      {
        "minuto": 53,
        "jugador": "Mohamed Touré",
        "resultado": "MissedShots",
        "x": 90.5,
        "y": 44.8,
        "arco_y": 92.9,
        "arco_z": 2.8
      },
      {
        "minuto": 74,
        "jugador": "Connor Metcalfe",
        "resultado": "Goal",
        "x": 75.7,
        "y": 43.4,
        "arco_y": 46.3,
        "arco_z": 4.4
      }
    ],
    "acciones": [
      {
        "id": 442302,
        "nombre": "Connor Metcalfe",
        "acciones": [
          {
            "tipo": "Aerial",
            "x": 74.7,
            "y": 23.5,
            "exitoso": false
          },
          {
            "tipo": "BallRecovery",
            "x": 70.1,
            "y": 13.4,
            "exitoso": true
          },
          {
            "tipo": "TakeOn",
            "x": 79.6,
            "y": 5.4,
            "exitoso": true
          },
          {
            "tipo": "Aerial",
            "x": 7.4,
            "y": 46.1,
            "exitoso": true
          },
          {
            "tipo": "Clearance",
            "x": 7.4,
            "y": 46.1,
            "exitoso": true
          },
          {
            "tipo": "BallRecovery",
            "x": 40.2,
            "y": 13.7,
            "exitoso": true
          },
          {
            "tipo": "Aerial",
            "x": 83.0,
            "y": 10.6,
            "exitoso": false
          },
          {
            "tipo": "Aerial",
            "x": 40.4,
            "y": 61.7,
            "exitoso": true
          },
          {
            "tipo": "Aerial",
            "x": 68.2,
            "y": 17.9,
            "exitoso": false
          },
          {
            "tipo": "Aerial",
            "x": 79.3,
            "y": 22.3,
            "exitoso": false
          },
          {
            "tipo": "Clearance",
            "x": 21.9,
            "y": 43.5,
            "exitoso": true
          },
          {
            "tipo": "BlockedPass",
            "x": 24.2,
            "y": 25.0,
            "exitoso": true
          },
          {
            "tipo": "Challenge",
            "x": 58.5,
            "y": 64.6,
            "exitoso": false
          },
          {
            "tipo": "Tackle",
            "x": 10.0,
            "y": 26.4,
            "exitoso": false
          },
          {
            "tipo": "Clearance",
            "x": 15.4,
            "y": 49.8,
            "exitoso": true
          },
          {
            "tipo": "BallRecovery",
            "x": 10.0,
            "y": 11.2,
            "exitoso": true
          },
          {
            "tipo": "BallRecovery",
            "x": 63.3,
            "y": 9.7,
            "exitoso": true
          }
        ]
      },
      {
        "id": 445546,
        "nombre": "Jacob Italiano",
        "acciones": [
          {
            "tipo": "BlockedPass",
            "x": 91.6,
            "y": 3.5,
            "exitoso": true
          },
          {
            "tipo": "Clearance",
            "x": 7.5,
            "y": 15.0,
            "exitoso": true
          },
          {
            "tipo": "Interception",
            "x": 29.2,
            "y": 10.1,
            "exitoso": true
          },
          {
            "tipo": "Dispossessed",
            "x": 36.2,
            "y": 14.4,
            "exitoso": true
          },
          {
            "tipo": "Tackle",
            "x": 29.0,
            "y": 3.8,
            "exitoso": false
          },
          {
            "tipo": "Tackle",
            "x": 2.0,
            "y": 13.2,
            "exitoso": false
          },
          {
            "tipo": "Aerial",
            "x": 53.4,
            "y": 19.6,
            "exitoso": false
          },
          {
            "tipo": "Clearance",
            "x": 12.2,
            "y": 34.6,
            "exitoso": true
          },
          {
            "tipo": "Tackle",
            "x": 29.0,
            "y": 7.7,
            "exitoso": true
          },
          {
            "tipo": "Clearance",
            "x": 1.2,
            "y": 17.4,
            "exitoso": true
          },
          {
            "tipo": "Clearance",
            "x": 10.2,
            "y": 31.4,
            "exitoso": true
          },
          {
            "tipo": "Clearance",
            "x": 13.9,
            "y": 20.3,
            "exitoso": true
          },
          {
            "tipo": "Clearance",
            "x": 13.9,
            "y": 14.5,
            "exitoso": true
          },
          {
            "tipo": "BlockedPass",
            "x": 54.3,
            "y": 49.5,
            "exitoso": true
          },
          {
            "tipo": "Clearance",
            "x": 4.1,
            "y": 50.0,
            "exitoso": true
          },
          {
            "tipo": "Clearance",
            "x": 13.8,
            "y": 44.5,
            "exitoso": true
          },
          {
            "tipo": "Challenge",
            "x": 8.2,
            "y": 22.6,
            "exitoso": false
          }
        ]
      },
      {
        "id": 323097,
        "nombre": "Aiden O'Neill",
        "acciones": [
          {
            "tipo": "Foul",
            "x": 64.8,
            "y": 23.4,
            "exitoso": false
          },
          {
            "tipo": "Clearance",
            "x": 8.8,
            "y": 70.2,
            "exitoso": true
          },
          {
            "tipo": "BallRecovery",
            "x": 66.6,
            "y": 48.9,
            "exitoso": true
          },
          {
            "tipo": "Clearance",
            "x": 25.9,
            "y": 29.3,
            "exitoso": true
          },
          {
            "tipo": "TakeOn",
            "x": 58.6,
            "y": 51.6,
            "exitoso": true
          },
          {
            "tipo": "BallRecovery",
            "x": 60.6,
            "y": 61.7,
            "exitoso": true
          },
          {
            "tipo": "Clearance",
            "x": 3.5,
            "y": 50.2,
            "exitoso": true
          },
          {
            "tipo": "Clearance",
            "x": 5.1,
            "y": 63.1,
            "exitoso": true
          },
          {
            "tipo": "Clearance",
            "x": 23.2,
            "y": 63.8,
            "exitoso": true
          },
          {
            "tipo": "Foul",
            "x": 36.0,
            "y": 89.2,
            "exitoso": true
          },
          {
            "tipo": "BallRecovery",
            "x": 36.7,
            "y": 25.8,
            "exitoso": true
          },
          {
            "tipo": "BallRecovery",
            "x": 33.6,
            "y": 48.5,
            "exitoso": true
          }
        ]
      },
      {
        "id": 477369,
        "nombre": "Nestory Irankunda",
        "acciones": [
          {
            "tipo": "Dispossessed",
            "x": 77.2,
            "y": 48.6,
            "exitoso": true
          },
          {
            "tipo": "TakeOn",
            "x": 81.9,
            "y": 69.2,
            "exitoso": true
          },
          {
            "tipo": "Clearance",
            "x": 23.5,
            "y": 70.2,
            "exitoso": true
          },
          {
            "tipo": "Foul",
            "x": 35.8,
            "y": 86.1,
            "exitoso": false
          },
          {
            "tipo": "Clearance",
            "x": 22.3,
            "y": 67.7,
            "exitoso": true
          },
          {
            "tipo": "Aerial",
            "x": 63.9,
            "y": 40.8,
            "exitoso": false
          },
          {
            "tipo": "BallRecovery",
            "x": 23.2,
            "y": 55.5,
            "exitoso": true
          },
          {
            "tipo": "Dispossessed",
            "x": 32.4,
            "y": 58.7,
            "exitoso": true
          },
          {
            "tipo": "Aerial",
            "x": 60.7,
            "y": 80.3,
            "exitoso": false
          },
          {
            "tipo": "Foul",
            "x": 56.8,
            "y": 83.2,
            "exitoso": true
          }
        ]
      },
      {
        "id": 344380,
        "nombre": "Harry Souttar",
        "acciones": [
          {
            "tipo": "Aerial",
            "x": 8.1,
            "y": 45.5,
            "exitoso": false
          },
          {
            "tipo": "Tackle",
            "x": 25.8,
            "y": 39.0,
            "exitoso": false
          },
          {
            "tipo": "Clearance",
            "x": 11.9,
            "y": 48.3,
            "exitoso": true
          },
          {
            "tipo": "Foul",
            "x": 40.3,
            "y": 27.8,
            "exitoso": false
          },
          {
            "tipo": "TakeOn",
            "x": 34.1,
            "y": 3.5,
            "exitoso": true
          },
          {
            "tipo": "Clearance",
            "x": 13.2,
            "y": 35.7,
            "exitoso": true
          },
          {
            "tipo": "Tackle",
            "x": 19.1,
            "y": 47.2,
            "exitoso": false
          },
          {
            "tipo": "Clearance",
            "x": 13.7,
            "y": 34.5,
            "exitoso": true
          },
          {
            "tipo": "Clearance",
            "x": 13.5,
            "y": 41.5,
            "exitoso": true
          },
          {
            "tipo": "Aerial",
            "x": 3.7,
            "y": 48.2,
            "exitoso": true
          },
          {
            "tipo": "Clearance",
            "x": 3.7,
            "y": 48.2,
            "exitoso": true
          },
          {
            "tipo": "Clearance",
            "x": 13.1,
            "y": 44.2,
            "exitoso": true
          },
          {
            "tipo": "Clearance",
            "x": 14.9,
            "y": 46.2,
            "exitoso": true
          },
          {
            "tipo": "Aerial",
            "x": 87.7,
            "y": 25.5,
            "exitoso": true
          },
          {
            "tipo": "Clearance",
            "x": 13.7,
            "y": 56.6,
            "exitoso": true
          },
          {
            "tipo": "Aerial",
            "x": 46.6,
            "y": 35.0,
            "exitoso": true
          },
          {
            "tipo": "Clearance",
            "x": 5.0,
            "y": 50.8,
            "exitoso": true
          },
          {
            "tipo": "Clearance",
            "x": 13.0,
            "y": 49.1,
            "exitoso": true
          },
          {
            "tipo": "Clearance",
            "x": 5.1,
            "y": 41.8,
            "exitoso": true
          },
          {
            "tipo": "Clearance",
            "x": 4.4,
            "y": 44.0,
            "exitoso": true
          },
          {
            "tipo": "Clearance",
            "x": 10.5,
            "y": 41.8,
            "exitoso": true
          }
        ]
      },
      {
        "id": 447486,
        "nombre": "Alessandro Circati",
        "acciones": [
          {
            "tipo": "Clearance",
            "x": 7.4,
            "y": 55.4,
            "exitoso": true
          },
          {
            "tipo": "Foul",
            "x": 64.4,
            "y": 5.6,
            "exitoso": false
          },
          {
            "tipo": "Clearance",
            "x": 18.5,
            "y": 51.9,
            "exitoso": true
          },
          {
            "tipo": "BallRecovery",
            "x": 61.5,
            "y": 6.7,
            "exitoso": true
          },
          {
            "tipo": "Clearance",
            "x": 10.8,
            "y": 42.1,
            "exitoso": true
          },
          {
            "tipo": "Clearance",
            "x": 7.8,
            "y": 35.5,
            "exitoso": true
          },
          {
            "tipo": "Dispossessed",
            "x": 14.8,
            "y": 27.4,
            "exitoso": true
          },
          {
            "tipo": "Aerial",
            "x": 93.8,
            "y": 34.0,
            "exitoso": false
          },
          {
            "tipo": "TakeOn",
            "x": 90.6,
            "y": 26.4,
            "exitoso": true
          },
          {
            "tipo": "Dispossessed",
            "x": 86.8,
            "y": 33.0,
            "exitoso": true
          },
          {
            "tipo": "Aerial",
            "x": 4.7,
            "y": 56.8,
            "exitoso": true
          },
          {
            "tipo": "Clearance",
            "x": 4.7,
            "y": 56.8,
            "exitoso": true
          },
          {
            "tipo": "Clearance",
            "x": 13.6,
            "y": 28.9,
            "exitoso": true
          },
          {
            "tipo": "BallRecovery",
            "x": 15.5,
            "y": 22.0,
            "exitoso": true
          },
          {
            "tipo": "BallRecovery",
            "x": 20.9,
            "y": 43.4,
            "exitoso": true
          },
          {
            "tipo": "Interception",
            "x": 6.4,
            "y": 33.6,
            "exitoso": true
          },
          {
            "tipo": "Tackle",
            "x": 27.6,
            "y": 30.5,
            "exitoso": true
          },
          {
            "tipo": "Tackle",
            "x": 9.2,
            "y": 29.5,
            "exitoso": false
          }
        ]
      },
      {
        "id": 570078,
        "nombre": "Paul Okon-Engstler",
        "acciones": [
          {
            "tipo": "BallRecovery",
            "x": 27.3,
            "y": 53.9,
            "exitoso": true
          },
          {
            "tipo": "BlockedPass",
            "x": 58.6,
            "y": 95.9,
            "exitoso": true
          },
          {
            "tipo": "Clearance",
            "x": 7.6,
            "y": 56.7,
            "exitoso": true
          },
          {
            "tipo": "Tackle",
            "x": 9.1,
            "y": 85.2,
            "exitoso": false
          },
          {
            "tipo": "Tackle",
            "x": 31.1,
            "y": 79.5,
            "exitoso": true
          },
          {
            "tipo": "Aerial",
            "x": 76.8,
            "y": 33.2,
            "exitoso": false
          },
          {
            "tipo": "TakeOn",
            "x": 15.2,
            "y": 97.2,
            "exitoso": false
          },
          {
            "tipo": "Clearance",
            "x": 18.5,
            "y": 54.4,
            "exitoso": true
          },
          {
            "tipo": "Interception",
            "x": 65.6,
            "y": 85.9,
            "exitoso": true
          },
          {
            "tipo": "BlockedPass",
            "x": 27.5,
            "y": 43.6,
            "exitoso": true
          },
          {
            "tipo": "Clearance",
            "x": 18.1,
            "y": 46.2,
            "exitoso": true
          },
          {
            "tipo": "Clearance",
            "x": 11.6,
            "y": 41.0,
            "exitoso": true
          },
          {
            "tipo": "BallRecovery",
            "x": 11.1,
            "y": 30.6,
            "exitoso": true
          },
          {
            "tipo": "Interception",
            "x": 23.0,
            "y": 37.9,
            "exitoso": true
          },
          {
            "tipo": "Challenge",
            "x": 21.4,
            "y": 50.0,
            "exitoso": false
          },
          {
            "tipo": "Foul",
            "x": 26.8,
            "y": 54.6,
            "exitoso": false
          },
          {
            "tipo": "Aerial",
            "x": 38.1,
            "y": 34.2,
            "exitoso": true
          },
          {
            "tipo": "Interception",
            "x": 19.8,
            "y": 38.6,
            "exitoso": true
          },
          {
            "tipo": "Tackle",
            "x": 19.9,
            "y": 53.3,
            "exitoso": false
          },
          {
            "tipo": "BallRecovery",
            "x": 40.5,
            "y": 50.3,
            "exitoso": true
          },
          {
            "tipo": "Clearance",
            "x": 21.3,
            "y": 72.5,
            "exitoso": true
          }
        ]
      },
      {
        "id": 231118,
        "nombre": "Cameron Burgess",
        "acciones": [
          {
            "tipo": "Clearance",
            "x": 4.6,
            "y": 71.5,
            "exitoso": true
          },
          {
            "tipo": "Tackle",
            "x": 69.2,
            "y": 74.6,
            "exitoso": true
          },
          {
            "tipo": "Clearance",
            "x": 32.4,
            "y": 50.3,
            "exitoso": true
          },
          {
            "tipo": "Clearance",
            "x": 12.3,
            "y": 74.1,
            "exitoso": true
          },
          {
            "tipo": "BallRecovery",
            "x": 32.3,
            "y": 70.6,
            "exitoso": true
          },
          {
            "tipo": "Tackle",
            "x": 4.0,
            "y": 85.2,
            "exitoso": false
          },
          {
            "tipo": "Aerial",
            "x": 8.4,
            "y": 49.8,
            "exitoso": true
          },
          {
            "tipo": "Clearance",
            "x": 8.4,
            "y": 49.8,
            "exitoso": true
          },
          {
            "tipo": "Aerial",
            "x": 7.0,
            "y": 48.8,
            "exitoso": true
          },
          {
            "tipo": "Clearance",
            "x": 6.8,
            "y": 51.5,
            "exitoso": true
          },
          {
            "tipo": "Interception",
            "x": 13.1,
            "y": 64.4,
            "exitoso": true
          },
          {
            "tipo": "Clearance",
            "x": 11.0,
            "y": 55.5,
            "exitoso": true
          }
        ]
      },
      {
        "id": 481083,
        "nombre": "Mohamed Touré",
        "acciones": [
          {
            "tipo": "Dispossessed",
            "x": 97.4,
            "y": 16.4,
            "exitoso": true
          },
          {
            "tipo": "Aerial",
            "x": 92.0,
            "y": 50.2,
            "exitoso": false
          },
          {
            "tipo": "TakeOn",
            "x": 92.8,
            "y": 16.9,
            "exitoso": false
          },
          {
            "tipo": "Foul",
            "x": 44.9,
            "y": 31.3,
            "exitoso": true
          },
          {
            "tipo": "Foul",
            "x": 74.2,
            "y": 13.1,
            "exitoso": false
          },
          {
            "tipo": "Aerial",
            "x": 87.4,
            "y": 19.6,
            "exitoso": false
          },
          {
            "tipo": "TakeOn",
            "x": 32.6,
            "y": 52.2,
            "exitoso": true
          },
          {
            "tipo": "TakeOn",
            "x": 32.8,
            "y": 53.0,
            "exitoso": false
          },
          {
            "tipo": "Foul",
            "x": 45.2,
            "y": 45.3,
            "exitoso": false
          },
          {
            "tipo": "BallRecovery",
            "x": 25.1,
            "y": 42.6,
            "exitoso": true
          },
          {
            "tipo": "TakeOn",
            "x": 31.0,
            "y": 41.4,
            "exitoso": true
          }
        ]
      },
      {
        "id": 599694,
        "nombre": "Patrick Beach",
        "acciones": [
          {
            "tipo": "BallRecovery",
            "x": 11.8,
            "y": 76.9,
            "exitoso": true
          }
        ]
      },
      {
        "id": 476544,
        "nombre": "Jordan Bos",
        "acciones": [
          {
            "tipo": "Dispossessed",
            "x": 36.8,
            "y": 72.8,
            "exitoso": true
          },
          {
            "tipo": "TakeOn",
            "x": 23.1,
            "y": 93.5,
            "exitoso": true
          },
          {
            "tipo": "Aerial",
            "x": 49.6,
            "y": 97.0,
            "exitoso": false
          },
          {
            "tipo": "Aerial",
            "x": 78.5,
            "y": 95.9,
            "exitoso": false
          },
          {
            "tipo": "BallRecovery",
            "x": 31.7,
            "y": 91.6,
            "exitoso": true
          },
          {
            "tipo": "TakeOn",
            "x": 27.4,
            "y": 62.6,
            "exitoso": false
          },
          {
            "tipo": "Foul",
            "x": 35.6,
            "y": 94.8,
            "exitoso": true
          },
          {
            "tipo": "BallRecovery",
            "x": 26.4,
            "y": 93.1,
            "exitoso": true
          },
          {
            "tipo": "Challenge",
            "x": 14.2,
            "y": 72.6,
            "exitoso": false
          }
        ]
      }
    ]
  },
  "away": {
    "equipo": "Turkiye",
    "jugadores": [
      {
        "id": 108073,
        "nombre": "Abdülkerim Bardakci",
        "dorsal": 14,
        "x": 42.9,
        "y": 71.6,
        "toques": 132
      },
      {
        "id": 321958,
        "nombre": "Ferdi Kadioglu",
        "dorsal": 20,
        "x": 57.0,
        "y": 82.4,
        "toques": 134
      },
      {
        "id": 355870,
        "nombre": "Orkun Kökçü",
        "dorsal": 6,
        "x": 66.1,
        "y": 52.6,
        "toques": 57
      },
      {
        "id": 110373,
        "nombre": "Hakan Çalhanoglu",
        "dorsal": 10,
        "x": 58.5,
        "y": 58.6,
        "toques": 132
      },
      {
        "id": 415181,
        "nombre": "Arda Güler",
        "dorsal": 8,
        "x": 68.2,
        "y": 39.6,
        "toques": 114
      },
      {
        "id": 362555,
        "nombre": "Merih Demiral",
        "dorsal": 3,
        "x": 46.4,
        "y": 45.3,
        "toques": 89
      },
      {
        "id": 409291,
        "nombre": "Ismail Yüksek",
        "dorsal": 16,
        "x": 54.7,
        "y": 37.5,
        "toques": 80
      },
      {
        "id": 258840,
        "nombre": "Ugurcan Çakir",
        "dorsal": 23,
        "x": 15.2,
        "y": 52.6,
        "toques": 36
      },
      {
        "id": 421779,
        "nombre": "Baris Alper Yilmaz",
        "dorsal": 21,
        "x": 75.7,
        "y": 85.1,
        "toques": 32
      },
      {
        "id": 136481,
        "nombre": "Zeki Çelik",
        "dorsal": 2,
        "x": 60.6,
        "y": 17.8,
        "toques": 55
      },
      {
        "id": 402880,
        "nombre": "Kerem Aktürkoglu",
        "dorsal": 7,
        "x": 72.1,
        "y": 51.0,
        "toques": 25
      }
    ],
    "pases": [
      {
        "de": 108073,
        "a": 321958,
        "veces": 46
      },
      {
        "de": 108073,
        "a": 355870,
        "veces": 5
      },
      {
        "de": 110373,
        "a": 415181,
        "veces": 31
      },
      {
        "de": 110373,
        "a": 362555,
        "veces": 18
      },
      {
        "de": 108073,
        "a": 362555,
        "veces": 38
      },
      {
        "de": 108073,
        "a": 110373,
        "veces": 36
      },
      {
        "de": 362555,
        "a": 409291,
        "veces": 19
      },
      {
        "de": 108073,
        "a": 258840,
        "veces": 14
      },
      {
        "de": 108073,
        "a": 421779,
        "veces": 4
      },
      {
        "de": 110373,
        "a": 355870,
        "veces": 15
      },
      {
        "de": 355870,
        "a": 415181,
        "veces": 19
      },
      {
        "de": 110373,
        "a": 321958,
        "veces": 40
      },
      {
        "de": 321958,
        "a": 355870,
        "veces": 13
      },
      {
        "de": 321958,
        "a": 415181,
        "veces": 21
      },
      {
        "de": 136481,
        "a": 415181,
        "veces": 16
      },
      {
        "de": 409291,
        "a": 415181,
        "veces": 20
      },
      {
        "de": 110373,
        "a": 409291,
        "veces": 21
      },
      {
        "de": 108073,
        "a": 409291,
        "veces": 13
      },
      {
        "de": 136481,
        "a": 355870,
        "veces": 6
      },
      {
        "de": 136481,
        "a": 409291,
        "veces": 12
      },
      {
        "de": 321958,
        "a": 421779,
        "veces": 20
      },
      {
        "de": 110373,
        "a": 421779,
        "veces": 8
      },
      {
        "de": 110373,
        "a": 136481,
        "veces": 13
      },
      {
        "de": 258840,
        "a": 415181,
        "veces": 2
      },
      {
        "de": 136481,
        "a": 258840,
        "veces": 2
      },
      {
        "de": 362555,
        "a": 415181,
        "veces": 11
      },
      {
        "de": 258840,
        "a": 362555,
        "veces": 7
      },
      {
        "de": 108073,
        "a": 136481,
        "veces": 2
      },
      {
        "de": 355870,
        "a": 409291,
        "veces": 7
      },
      {
        "de": 110373,
        "a": 402880,
        "veces": 5
      },
      {
        "de": 321958,
        "a": 362555,
        "veces": 11
      },
      {
        "de": 136481,
        "a": 362555,
        "veces": 8
      },
      {
        "de": 355870,
        "a": 362555,
        "veces": 3
      },
      {
        "de": 355870,
        "a": 421779,
        "veces": 2
      },
      {
        "de": 321958,
        "a": 409291,
        "veces": 9
      },
      {
        "de": 258840,
        "a": 321958,
        "veces": 8
      },
      {
        "de": 415181,
        "a": 421779,
        "veces": 3
      },
      {
        "de": 321958,
        "a": 402880,
        "veces": 4
      },
      {
        "de": 258840,
        "a": 409291,
        "veces": 3
      },
      {
        "de": 355870,
        "a": 402880,
        "veces": 1
      },
      {
        "de": 108073,
        "a": 415181,
        "veces": 7
      },
      {
        "de": 402880,
        "a": 409291,
        "veces": 1
      },
      {
        "de": 136481,
        "a": 321958,
        "veces": 2
      },
      {
        "de": 402880,
        "a": 415181,
        "veces": 3
      },
      {
        "de": 362555,
        "a": 421779,
        "veces": 1
      },
      {
        "de": 402880,
        "a": 421779,
        "veces": 1
      },
      {
        "de": 110373,
        "a": 258840,
        "veces": 2
      },
      {
        "de": 136481,
        "a": 402880,
        "veces": 1
      },
      {
        "de": 362555,
        "a": 402880,
        "veces": 1
      }
    ],
    "estadisticas": {
      "tiros": 30,
      "tiros_al_arco": 20,
      "pases_totales": 758,
      "precision_pases": 87.6,
      "posesion": 62.8,
      "goles": []
    },
    "tiros": [
      {
        "minuto": 2,
        "jugador": "Hakan Çalhanoglu",
        "resultado": "SavedShot",
        "x": 73.8,
        "y": 51.1,
        "arco_y": 52.7,
        "arco_z": 19.0
      },
      {
        "minuto": 3,
        "jugador": "Ismail Yüksek",
        "resultado": "SavedShot",
        "x": 91.9,
        "y": 54.5,
        "arco_y": 50.8,
        "arco_z": 19.0
      },
      {
        "minuto": 6,
        "jugador": "Arda Güler",
        "resultado": "MissedShots",
        "x": 85.3,
        "y": 28.6,
        "arco_y": 59.3,
        "arco_z": 77.8
      },
      {
        "minuto": 18,
        "jugador": "Ferdi Kadioglu",
        "resultado": "MissedShots",
        "x": 78.1,
        "y": 60.5,
        "arco_y": 45.7,
        "arco_z": 76.4
      },
      {
        "minuto": 26,
        "jugador": "Arda Güler",
        "resultado": "SavedShot",
        "x": 86.0,
        "y": 47.7,
        "arco_y": 51.6,
        "arco_z": 7.6
      },
      {
        "minuto": 29,
        "jugador": "Abdülkerim Bardakci",
        "resultado": "SavedShot",
        "x": 72.4,
        "y": 57.2,
        "arco_y": 54.0,
        "arco_z": 20.9
      },
      {
        "minuto": 29,
        "jugador": "Hakan Çalhanoglu",
        "resultado": "MissedShots",
        "x": 73.2,
        "y": 29.3,
        "arco_y": 41.8,
        "arco_z": 65.3
      },
      {
        "minuto": 35,
        "jugador": "Orkun Kökçü",
        "resultado": "MissedShots",
        "x": 87.1,
        "y": 58.2,
        "arco_y": 33.8,
        "arco_z": 26.4
      },
      {
        "minuto": 41,
        "jugador": "Arda Güler",
        "resultado": "MissedShots",
        "x": 74.7,
        "y": 45.2,
        "arco_y": 58.8,
        "arco_z": 68.1
      },
      {
        "minuto": 45,
        "jugador": "Hakan Çalhanoglu",
        "resultado": "SavedShot",
        "x": 76.6,
        "y": 73.8,
        "arco_y": 49.4,
        "arco_z": 15.8
      },
      {
        "minuto": 48,
        "jugador": "Kerem Aktürkoglu",
        "resultado": "SavedShot",
        "x": 87.4,
        "y": 48.6,
        "arco_y": 51.7,
        "arco_z": 19.0
      },
      {
        "minuto": 49,
        "jugador": "Hakan Çalhanoglu",
        "resultado": "SavedShot",
        "x": 85.0,
        "y": 47.6,
        "arco_y": 50.1,
        "arco_z": 19.0
      },
      {
        "minuto": 49,
        "jugador": "Ismail Yüksek",
        "resultado": "SavedShot",
        "x": 79.8,
        "y": 49.2,
        "arco_y": 49.9,
        "arco_z": 19.0
      },
      {
        "minuto": 50,
        "jugador": "Kerem Aktürkoglu",
        "resultado": "MissedShots",
        "x": 76.5,
        "y": 46.6,
        "arco_y": 60.8,
        "arco_z": 15.3
      },
      {
        "minuto": 56,
        "jugador": "Arda Güler",
        "resultado": "SavedShot",
        "x": 73.2,
        "y": 43.0,
        "arco_y": 53.4,
        "arco_z": 7.0
      },
      {
        "minuto": 56,
        "jugador": "Ismail Yüksek",
        "resultado": "MissedShots",
        "x": 87.4,
        "y": 41.7,
        "arco_y": 44.9,
        "arco_z": 88.9
      },
      {
        "minuto": 59,
        "jugador": "Kenan Yildiz",
        "resultado": "SavedShot",
        "x": 89.2,
        "y": 63.2,
        "arco_y": 50.6,
        "arco_z": 19.0
      },
      {
        "minuto": 62,
        "jugador": "Kenan Yildiz",
        "resultado": "SavedShot",
        "x": 78.7,
        "y": 72.1,
        "arco_y": 50.1,
        "arco_z": 19.0
      },
      {
        "minuto": 64,
        "jugador": "Arda Güler",
        "resultado": "SavedShot",
        "x": 74.5,
        "y": 63.6,
        "arco_y": 51.1,
        "arco_z": 19.0
      },
      {
        "minuto": 65,
        "jugador": "Kenan Yildiz",
        "resultado": "SavedShot",
        "x": 86.8,
        "y": 75.2,
        "arco_y": 49.6,
        "arco_z": 19.0
      },
      {
        "minuto": 65,
        "jugador": "Kenan Yildiz",
        "resultado": "SavedShot",
        "x": 84.9,
        "y": 64.1,
        "arco_y": 50.7,
        "arco_z": 19.0
      },
      {
        "minuto": 71,
        "jugador": "Zeki Çelik",
        "resultado": "SavedShot",
        "x": 97.7,
        "y": 35.6,
        "arco_y": 45.8,
        "arco_z": 13.3
      },
      {
        "minuto": 73,
        "jugador": "Arda Güler",
        "resultado": "MissedShots",
        "x": 76.8,
        "y": 32.5,
        "arco_y": 58.5,
        "arco_z": 69.4
      },
      {
        "minuto": 76,
        "jugador": "Kenan Yildiz",
        "resultado": "SavedShot",
        "x": 87.6,
        "y": 31.1,
        "arco_y": 49.9,
        "arco_z": 19.0
      },
      {
        "minuto": 77,
        "jugador": "Kerem Aktürkoglu",
        "resultado": "SavedShot",
        "x": 91.5,
        "y": 49.1,
        "arco_y": 50.0,
        "arco_z": 17.1
      },
      {
        "minuto": 81,
        "jugador": "Arda Güler",
        "resultado": "MissedShots",
        "x": 77.7,
        "y": 30.9,
        "arco_y": 59.8,
        "arco_z": 45.8
      },
      {
        "minuto": 85,
        "jugador": "Hakan Çalhanoglu",
        "resultado": "SavedShot",
        "x": 75.6,
        "y": 62.2,
        "arco_y": 45.4,
        "arco_z": 8.9
      },
      {
        "minuto": 88,
        "jugador": "Arda Güler",
        "resultado": "SavedShot",
        "x": 79.4,
        "y": 42.7,
        "arco_y": 50.3,
        "arco_z": 6.3
      },
      {
        "minuto": 90,
        "jugador": "Merih Demiral",
        "resultado": "MissedShots",
        "x": 92.1,
        "y": 37.2,
        "arco_y": 41.3,
        "arco_z": 43.1
      },
      {
        "minuto": 94,
        "jugador": "Kenan Yildiz",
        "resultado": "SavedShot",
        "x": 77.8,
        "y": 63.6,
        "arco_y": 50.3,
        "arco_z": 19.0
      }
    ],
    "acciones": [
      {
        "id": 108073,
        "nombre": "Abdülkerim Bardakci",
        "acciones": [
          {
            "tipo": "Aerial",
            "x": 25.3,
            "y": 76.5,
            "exitoso": true
          },
          {
            "tipo": "Clearance",
            "x": 25.3,
            "y": 76.5,
            "exitoso": true
          },
          {
            "tipo": "Aerial",
            "x": 92.6,
            "y": 53.9,
            "exitoso": false
          },
          {
            "tipo": "Tackle",
            "x": 2.6,
            "y": 83.6,
            "exitoso": true
          },
          {
            "tipo": "BallRecovery",
            "x": 41.5,
            "y": 71.8,
            "exitoso": true
          },
          {
            "tipo": "Aerial",
            "x": 8.0,
            "y": 49.8,
            "exitoso": true
          },
          {
            "tipo": "Clearance",
            "x": 8.0,
            "y": 49.8,
            "exitoso": true
          },
          {
            "tipo": "BallRecovery",
            "x": 25.4,
            "y": 77.4,
            "exitoso": true
          },
          {
            "tipo": "Clearance",
            "x": 16.5,
            "y": 85.8,
            "exitoso": true
          },
          {
            "tipo": "Aerial",
            "x": 31.8,
            "y": 82.1,
            "exitoso": true
          },
          {
            "tipo": "Clearance",
            "x": 31.8,
            "y": 82.1,
            "exitoso": true
          },
          {
            "tipo": "Clearance",
            "x": 23.7,
            "y": 83.4,
            "exitoso": true
          },
          {
            "tipo": "Aerial",
            "x": 20.7,
            "y": 77.7,
            "exitoso": true
          },
          {
            "tipo": "Aerial",
            "x": 96.3,
            "y": 51.8,
            "exitoso": false
          },
          {
            "tipo": "Aerial",
            "x": 91.6,
            "y": 50.2,
            "exitoso": false
          },
          {
            "tipo": "Aerial",
            "x": 12.3,
            "y": 74.5,
            "exitoso": false
          },
          {
            "tipo": "Challenge",
            "x": 69.0,
            "y": 58.6,
            "exitoso": false
          },
          {
            "tipo": "BallRecovery",
            "x": 20.4,
            "y": 96.2,
            "exitoso": true
          },
          {
            "tipo": "Foul",
            "x": 36.0,
            "y": 69.7,
            "exitoso": true
          },
          {
            "tipo": "Tackle",
            "x": 33.0,
            "y": 47.6,
            "exitoso": true
          },
          {
            "tipo": "Clearance",
            "x": 3.8,
            "y": 51.7,
            "exitoso": true
          },
          {
            "tipo": "Aerial",
            "x": 6.5,
            "y": 73.1,
            "exitoso": false
          },
          {
            "tipo": "Foul",
            "x": 36.0,
            "y": 93.2,
            "exitoso": true
          },
          {
            "tipo": "Interception",
            "x": 27.1,
            "y": 49.4,
            "exitoso": true
          },
          {
            "tipo": "BallRecovery",
            "x": 29.0,
            "y": 33.6,
            "exitoso": true
          },
          {
            "tipo": "TakeOn",
            "x": 70.1,
            "y": 48.4,
            "exitoso": true
          },
          {
            "tipo": "Dispossessed",
            "x": 71.4,
            "y": 53.3,
            "exitoso": true
          },
          {
            "tipo": "Aerial",
            "x": 30.1,
            "y": 81.2,
            "exitoso": false
          }
        ]
      },
      {
        "id": 321958,
        "nombre": "Ferdi Kadioglu",
        "acciones": [
          {
            "tipo": "BallRecovery",
            "x": 8.8,
            "y": 91.7,
            "exitoso": true
          },
          {
            "tipo": "Clearance",
            "x": 8.4,
            "y": 78.0,
            "exitoso": true
          },
          {
            "tipo": "Aerial",
            "x": 46.6,
            "y": 80.4,
            "exitoso": true
          },
          {
            "tipo": "BallRecovery",
            "x": 61.6,
            "y": 87.6,
            "exitoso": true
          },
          {
            "tipo": "Aerial",
            "x": 17.0,
            "y": 89.4,
            "exitoso": true
          },
          {
            "tipo": "Clearance",
            "x": 14.0,
            "y": 84.2,
            "exitoso": true
          },
          {
            "tipo": "Clearance",
            "x": 22.5,
            "y": 83.5,
            "exitoso": true
          },
          {
            "tipo": "Aerial",
            "x": 59.6,
            "y": 38.3,
            "exitoso": false
          },
          {
            "tipo": "BallRecovery",
            "x": 71.7,
            "y": 92.1,
            "exitoso": true
          },
          {
            "tipo": "BallRecovery",
            "x": 64.2,
            "y": 65.2,
            "exitoso": true
          },
          {
            "tipo": "Clearance",
            "x": 34.7,
            "y": 60.5,
            "exitoso": true
          },
          {
            "tipo": "Clearance",
            "x": 2.3,
            "y": 81.8,
            "exitoso": true
          },
          {
            "tipo": "BallRecovery",
            "x": 28.8,
            "y": 37.0,
            "exitoso": true
          },
          {
            "tipo": "BallRecovery",
            "x": 12.1,
            "y": 85.6,
            "exitoso": true
          }
        ]
      },
      {
        "id": 355870,
        "nombre": "Orkun Kökçü",
        "acciones": [
          {
            "tipo": "TakeOn",
            "x": 29.1,
            "y": 79.9,
            "exitoso": false
          },
          {
            "tipo": "Foul",
            "x": 35.2,
            "y": 76.6,
            "exitoso": true
          },
          {
            "tipo": "Dispossessed",
            "x": 74.2,
            "y": 61.0,
            "exitoso": true
          },
          {
            "tipo": "Foul",
            "x": 35.6,
            "y": 94.4,
            "exitoso": true
          },
          {
            "tipo": "BallRecovery",
            "x": 67.8,
            "y": 52.9,
            "exitoso": true
          },
          {
            "tipo": "BlockedPass",
            "x": 81.9,
            "y": 44.0,
            "exitoso": true
          },
          {
            "tipo": "Tackle",
            "x": 85.2,
            "y": 72.6,
            "exitoso": false
          },
          {
            "tipo": "Challenge",
            "x": 41.4,
            "y": 48.4,
            "exitoso": false
          },
          {
            "tipo": "Clearance",
            "x": 19.4,
            "y": 42.3,
            "exitoso": true
          },
          {
            "tipo": "BallRecovery",
            "x": 71.1,
            "y": 37.1,
            "exitoso": true
          },
          {
            "tipo": "Foul",
            "x": 73.2,
            "y": 45.4,
            "exitoso": true
          }
        ]
      },
      {
        "id": 110373,
        "nombre": "Hakan Çalhanoglu",
        "acciones": [
          {
            "tipo": "Challenge",
            "x": 20.4,
            "y": 94.6,
            "exitoso": false
          },
          {
            "tipo": "BallRecovery",
            "x": 27.1,
            "y": 60.0,
            "exitoso": true
          },
          {
            "tipo": "BallRecovery",
            "x": 43.0,
            "y": 92.1,
            "exitoso": true
          },
          {
            "tipo": "Interception",
            "x": 54.6,
            "y": 63.1,
            "exitoso": true
          },
          {
            "tipo": "Clearance",
            "x": 15.1,
            "y": 50.5,
            "exitoso": true
          },
          {
            "tipo": "BallRecovery",
            "x": 34.5,
            "y": 61.8,
            "exitoso": true
          },
          {
            "tipo": "BallRecovery",
            "x": 41.2,
            "y": 67.9,
            "exitoso": true
          },
          {
            "tipo": "Foul",
            "x": 25.7,
            "y": 87.0,
            "exitoso": true
          },
          {
            "tipo": "BallRecovery",
            "x": 33.4,
            "y": 69.1,
            "exitoso": true
          },
          {
            "tipo": "Foul",
            "x": 64.5,
            "y": 5.2,
            "exitoso": false
          },
          {
            "tipo": "Clearance",
            "x": 3.7,
            "y": 39.5,
            "exitoso": true
          },
          {
            "tipo": "Dispossessed",
            "x": 80.1,
            "y": 46.8,
            "exitoso": true
          },
          {
            "tipo": "BallRecovery",
            "x": 48.1,
            "y": 58.3,
            "exitoso": true
          },
          {
            "tipo": "Aerial",
            "x": 35.7,
            "y": 65.8,
            "exitoso": false
          },
          {
            "tipo": "BallRecovery",
            "x": 39.3,
            "y": 73.8,
            "exitoso": true
          }
        ]
      },
      {
        "id": 362555,
        "nombre": "Merih Demiral",
        "acciones": [
          {
            "tipo": "Clearance",
            "x": 6.1,
            "y": 56.1,
            "exitoso": true
          },
          {
            "tipo": "Tackle",
            "x": 7.2,
            "y": 83.1,
            "exitoso": true
          },
          {
            "tipo": "Challenge",
            "x": 18.1,
            "y": 30.8,
            "exitoso": false
          },
          {
            "tipo": "Aerial",
            "x": 12.6,
            "y": 80.4,
            "exitoso": true
          },
          {
            "tipo": "Clearance",
            "x": 12.6,
            "y": 80.4,
            "exitoso": true
          },
          {
            "tipo": "Clearance",
            "x": 33.9,
            "y": 10.0,
            "exitoso": true
          },
          {
            "tipo": "Aerial",
            "x": 36.1,
            "y": 59.2,
            "exitoso": true
          },
          {
            "tipo": "Foul",
            "x": 54.8,
            "y": 54.7,
            "exitoso": true
          },
          {
            "tipo": "Clearance",
            "x": 24.9,
            "y": 45.3,
            "exitoso": true
          },
          {
            "tipo": "Clearance",
            "x": 23.8,
            "y": 74.9,
            "exitoso": true
          },
          {
            "tipo": "Clearance",
            "x": 21.1,
            "y": 62.3,
            "exitoso": true
          },
          {
            "tipo": "Clearance",
            "x": 36.7,
            "y": 29.2,
            "exitoso": true
          },
          {
            "tipo": "Aerial",
            "x": 28.0,
            "y": 57.2,
            "exitoso": true
          },
          {
            "tipo": "Aerial",
            "x": 38.7,
            "y": 11.4,
            "exitoso": false
          },
          {
            "tipo": "Aerial",
            "x": 92.1,
            "y": 37.2,
            "exitoso": true
          },
          {
            "tipo": "Aerial",
            "x": 85.2,
            "y": 71.7,
            "exitoso": true
          },
          {
            "tipo": "TakeOn",
            "x": 90.8,
            "y": 70.4,
            "exitoso": false
          },
          {
            "tipo": "Aerial",
            "x": 88.0,
            "y": 63.9,
            "exitoso": false
          }
        ]
      },
      {
        "id": 409291,
        "nombre": "Ismail Yüksek",
        "acciones": [
          {
            "tipo": "Clearance",
            "x": 14.2,
            "y": 56.8,
            "exitoso": true
          },
          {
            "tipo": "Tackle",
            "x": 22.8,
            "y": 51.4,
            "exitoso": true
          },
          {
            "tipo": "Aerial",
            "x": 91.9,
            "y": 54.5,
            "exitoso": true
          },
          {
            "tipo": "Clearance",
            "x": 12.2,
            "y": 38.0,
            "exitoso": true
          },
          {
            "tipo": "BallRecovery",
            "x": 38.5,
            "y": 5.6,
            "exitoso": true
          },
          {
            "tipo": "Foul",
            "x": 55.1,
            "y": 68.7,
            "exitoso": false
          },
          {
            "tipo": "BallRecovery",
            "x": 40.3,
            "y": 37.0,
            "exitoso": true
          },
          {
            "tipo": "Tackle",
            "x": 67.2,
            "y": 47.0,
            "exitoso": true
          },
          {
            "tipo": "TakeOn",
            "x": 78.6,
            "y": 50.0,
            "exitoso": true
          },
          {
            "tipo": "Clearance",
            "x": 34.5,
            "y": 18.0,
            "exitoso": true
          },
          {
            "tipo": "Tackle",
            "x": 67.6,
            "y": 41.3,
            "exitoso": true
          },
          {
            "tipo": "Aerial",
            "x": 39.3,
            "y": 19.7,
            "exitoso": true
          },
          {
            "tipo": "BlockedPass",
            "x": 59.8,
            "y": 79.5,
            "exitoso": true
          },
          {
            "tipo": "BlockedPass",
            "x": 37.5,
            "y": 62.6,
            "exitoso": true
          },
          {
            "tipo": "Clearance",
            "x": 11.8,
            "y": 85.1,
            "exitoso": true
          }
        ]
      },
      {
        "id": 136481,
        "nombre": "Zeki Çelik",
        "acciones": [
          {
            "tipo": "Clearance",
            "x": 16.0,
            "y": 34.1,
            "exitoso": true
          },
          {
            "tipo": "Tackle",
            "x": 63.2,
            "y": 27.2,
            "exitoso": false
          },
          {
            "tipo": "Aerial",
            "x": 50.4,
            "y": 3.0,
            "exitoso": true
          },
          {
            "tipo": "Aerial",
            "x": 21.5,
            "y": 4.1,
            "exitoso": true
          },
          {
            "tipo": "Clearance",
            "x": 21.5,
            "y": 4.1,
            "exitoso": true
          },
          {
            "tipo": "BallRecovery",
            "x": 18.7,
            "y": 36.4,
            "exitoso": true
          },
          {
            "tipo": "Clearance",
            "x": 8.0,
            "y": 21.8,
            "exitoso": true
          },
          {
            "tipo": "Aerial",
            "x": 95.3,
            "y": 43.2,
            "exitoso": false
          },
          {
            "tipo": "Foul",
            "x": 43.2,
            "y": 16.8,
            "exitoso": false
          },
          {
            "tipo": "BallRecovery",
            "x": 56.4,
            "y": 27.6,
            "exitoso": true
          },
          {
            "tipo": "BallRecovery",
            "x": 74.4,
            "y": 35.1,
            "exitoso": true
          },
          {
            "tipo": "BallRecovery",
            "x": 68.5,
            "y": 43.3,
            "exitoso": true
          }
        ]
      },
      {
        "id": 415181,
        "nombre": "Arda Güler",
        "acciones": [
          {
            "tipo": "BallRecovery",
            "x": 42.0,
            "y": 4.4,
            "exitoso": true
          },
          {
            "tipo": "Dispossessed",
            "x": 30.8,
            "y": 25.4,
            "exitoso": true
          },
          {
            "tipo": "Challenge",
            "x": 76.9,
            "y": 6.5,
            "exitoso": false
          },
          {
            "tipo": "TakeOn",
            "x": 90.9,
            "y": 14.8,
            "exitoso": false
          },
          {
            "tipo": "TakeOn",
            "x": 68.9,
            "y": 20.5,
            "exitoso": false
          },
          {
            "tipo": "Foul",
            "x": 64.2,
            "y": 13.9,
            "exitoso": true
          },
          {
            "tipo": "Aerial",
            "x": 23.2,
            "y": 66.8,
            "exitoso": true
          },
          {
            "tipo": "Challenge",
            "x": 67.4,
            "y": 47.8,
            "exitoso": false
          },
          {
            "tipo": "TakeOn",
            "x": 80.9,
            "y": 52.8,
            "exitoso": false
          },
          {
            "tipo": "Challenge",
            "x": 9.4,
            "y": 73.6,
            "exitoso": false
          },
          {
            "tipo": "BallRecovery",
            "x": 67.2,
            "y": 6.6,
            "exitoso": true
          },
          {
            "tipo": "TakeOn",
            "x": 41.5,
            "y": 35.4,
            "exitoso": true
          },
          {
            "tipo": "Aerial",
            "x": 61.9,
            "y": 65.8,
            "exitoso": false
          },
          {
            "tipo": "BallRecovery",
            "x": 66.1,
            "y": 21.0,
            "exitoso": true
          },
          {
            "tipo": "TakeOn",
            "x": 90.1,
            "y": 73.5,
            "exitoso": false
          },
          {
            "tipo": "Interception",
            "x": 60.7,
            "y": 52.3,
            "exitoso": true
          },
          {
            "tipo": "Tackle",
            "x": 74.0,
            "y": 11.9,
            "exitoso": true
          },
          {
            "tipo": "Foul",
            "x": 65.4,
            "y": 9.8,
            "exitoso": true
          }
        ]
      },
      {
        "id": 421779,
        "nombre": "Baris Alper Yilmaz",
        "acciones": [
          {
            "tipo": "Tackle",
            "x": 63.8,
            "y": 85.6,
            "exitoso": false
          },
          {
            "tipo": "TakeOn",
            "x": 71.0,
            "y": 96.2,
            "exitoso": false
          },
          {
            "tipo": "TakeOn",
            "x": 98.0,
            "y": 86.8,
            "exitoso": false
          },
          {
            "tipo": "Dispossessed",
            "x": 71.0,
            "y": 92.3,
            "exitoso": true
          }
        ]
      },
      {
        "id": 258840,
        "nombre": "Ugurcan Çakir",
        "acciones": [
          {
            "tipo": "Clearance",
            "x": 31.3,
            "y": 60.0,
            "exitoso": true
          },
          {
            "tipo": "BallRecovery",
            "x": 23.1,
            "y": 55.0,
            "exitoso": true
          },
          {
            "tipo": "Clearance",
            "x": 19.9,
            "y": 65.0,
            "exitoso": true
          }
        ]
      },
      {
        "id": 402880,
        "nombre": "Kerem Aktürkoglu",
        "acciones": [
          {
            "tipo": "Foul",
            "x": 59.8,
            "y": 72.2,
            "exitoso": true
          },
          {
            "tipo": "Challenge",
            "x": 65.9,
            "y": 96.5,
            "exitoso": false
          },
          {
            "tipo": "Tackle",
            "x": 84.8,
            "y": 2.8,
            "exitoso": true
          },
          {
            "tipo": "TakeOn",
            "x": 96.0,
            "y": 14.8,
            "exitoso": false
          },
          {
            "tipo": "Aerial",
            "x": 93.0,
            "y": 51.2,
            "exitoso": false
          },
          {
            "tipo": "Aerial",
            "x": 53.4,
            "y": 65.0,
            "exitoso": false
          },
          {
            "tipo": "Foul",
            "x": 76.1,
            "y": 63.8,
            "exitoso": true
          }
        ]
      }
    ]
  }
}